casu/__init__.py
casu/py.typed
casu-0.1.0.dist-info/METADATA
casu-0.1.0.dist-info/WHEEL
casu-0.1.0.dist-info/RECORD
