Metadata-Version: 2.4
Name: casu
Version: 0.1.0
Summary: Add your description here
Author-email: meizuflux <hello@meizuflux.com>
Requires-Python: >=3.11
Requires-Dist: muffin>=0.102.3
